{
    "id":970353,
    "feedId":4,
    "feedEventId":"sr:match:22055821",
    "type":1,
    "status":1,
    "sportId":12,
    "sportName":"Soccer",
    "categoryId":78,
    "categoryName":"Austria",
    "tournamentId":129,
    "tournamentName":"Erste Liga",
    "name":"SKU Amstetten - SK Austria Klagenfurt",
    "description":null,
    "startAt":"2020-07-24 18:30:00",
    "active":1,
    "deleted":0,
    "markets":{
       "14":{
          "id":14,
          "name":"PRVO POLUVREME",
          "sourceId":1,
          "eventType":1,
          "isCompetitor":0,
          "marketOutcomes":{
             "130":{
                "id":130,
                "marketId":14,
                "sourceId":1,
                "name":"P1",
                "active":1,
                "marketOutcomeSourceMaps":[
                   {
                      "id":31,
                      "marketOutcomeId":130,
                      "sourceId":2,
                      "sourceMarketOutcomeId":"60/1",
                      "marketOutcomeSourceMapSpecials":[
 
                      ]
                   }
                ]
             },
             "132":{
                "id":132,
                "marketId":14,
                "sourceId":1,
                "name":"PX",
                "active":1,
                "marketOutcomeSourceMaps":[
                   {
                      "id":32,
                      "marketOutcomeId":132,
                      "sourceId":2,
                      "sourceMarketOutcomeId":"60/2",
                      "marketOutcomeSourceMapSpecials":[
 
                      ]
                   }
                ]
             },
             "134":{
                "id":134,
                "marketId":14,
                "sourceId":1,
                "name":"P2",
                "active":1,
                "marketOutcomeSourceMaps":[
                   {
                      "id":33,
                      "marketOutcomeId":134,
                      "sourceId":2,
                      "sourceMarketOutcomeId":"60/3",
                      "marketOutcomeSourceMapSpecials":[
 
                      ]
                   }
                ]
             }
          },
          "marketSpecialValues":[
 
          ],
          "marketSourceMaps":[
             {
                "id":13,
                "marketId":14,
                "sourceId":2,
                "sourceMarketId":"60",
                "marketSourceMapSpecials":[
 
                ]
             }
          ],
          "marketCompetitors":[
 
          ]
       },
       "16":{
          "id":16,
          "name":"DUPLA SANSA PRVO POLUVREME",
          "sourceId":1,
          "eventType":1,
          "isCompetitor":0,
          "marketOutcomes":{
             "152":{
                "id":152,
                "marketId":16,
                "sourceId":1,
                "name":"1X PP",
                "active":1,
                "marketOutcomeSourceMaps":[
                   {
                      "id":119,
                      "marketOutcomeId":152,
                      "sourceId":2,
                      "sourceMarketOutcomeId":"63/9",
                      "marketOutcomeSourceMapSpecials":[
 
                      ]
                   }
                ]
             },
             "155":{
                "id":155,
                "marketId":16,
                "sourceId":1,
                "name":"12 PP",
                "active":1,
                "marketOutcomeSourceMaps":[
                   {
                      "id":155,
                      "marketOutcomeId":155,
                      "sourceId":2,
                      "sourceMarketOutcomeId":"63/10",
                      "marketOutcomeSourceMapSpecials":[
 
                      ]
                   }
                ]
             },
             "160":{
                "id":160,
                "marketId":16,
                "sourceId":1,
                "name":"X2 PP",
                "active":1,
                "marketOutcomeSourceMaps":[
                   {
                      "id":156,
                      "marketOutcomeId":160,
                      "sourceId":2,
                      "sourceMarketOutcomeId":"63/11",
                      "marketOutcomeSourceMapSpecials":[
 
                      ]
                   }
                ]
             }
          },
          "marketSpecialValues":[
 
          ],
          "marketSourceMaps":[
             {
                "id":105,
                "marketId":16,
                "sourceId":2,
                "sourceMarketId":"63",
                "marketSourceMapSpecials":[
 
                ]
             }
          ],
          "marketCompetitors":[
 
          ]
       },
       "24":{
          "id":24,
          "name":"VINER",
          "sourceId":1,
          "eventType":1,
          "isCompetitor":0,
          "marketOutcomes":{
             "238":{
                "id":238,
                "marketId":24,
                "sourceId":1,
                "name":"W1",
                "active":1,
                "marketOutcomeSourceMaps":[
 
                ]
             },
             "239":{
                "id":239,
                "marketId":24,
                "sourceId":1,
                "name":"W2",
                "active":1,
                "marketOutcomeSourceMaps":[
 
                ]
             }
          },
          "marketSpecialValues":[
 
          ],
          "marketSourceMaps":[
 
          ],
          "marketCompetitors":[
 
          ]
       },
       "31":{
          "id":31,
          "name":"PADA VISE GOLOVA",
          "sourceId":1,
          "eventType":1,
          "isCompetitor":0,
          "marketOutcomes":{
             "192":{
                "id":192,
                "marketId":31,
                "sourceId":1,
                "name":"I >",
                "active":1,
                "marketOutcomeSourceMaps":[
                   {
                      "id":28,
                      "marketOutcomeId":192,
                      "sourceId":2,
                      "sourceMarketOutcomeId":"52/436",
                      "marketOutcomeSourceMapSpecials":[
 
                      ]
                   }
                ]
             },
             "193":{
                "id":193,
                "marketId":31,
                "sourceId":1,
                "name":"I = II",
                "active":1,
                "marketOutcomeSourceMaps":[
                   {
                      "id":29,
                      "marketOutcomeId":193,
                      "sourceId":2,
                      "sourceMarketOutcomeId":"52/440",
                      "marketOutcomeSourceMapSpecials":[
 
                      ]
                   }
                ]
             },
             "194":{
                "id":194,
                "marketId":31,
                "sourceId":1,
                "name":"II >",
                "active":1,
                "marketOutcomeSourceMaps":[
                   {
                      "id":30,
                      "marketOutcomeId":194,
                      "sourceId":2,
                      "sourceMarketOutcomeId":"52/438",
                      "marketOutcomeSourceMapSpecials":[
 
                      ]
                   }
                ]
             }
          },
          "marketSpecialValues":[
 
          ],
          "marketSourceMaps":[
             {
                "id":12,
                "marketId":31,
                "sourceId":2,
                "sourceMarketId":"52",
                "marketSourceMapSpecials":[
 
                ]
             }
          ],
          "marketCompetitors":[
 
          ]
       },
       "93":{
          "id":93,
          "name":"2nd half - handicap",
          "sourceId":1,
          "eventType":1,
          "isCompetitor":0,
          "marketOutcomes":{
             "486":{
                "id":486,
                "marketId":93,
                "sourceId":1,
                "name":"1",
                "active":1,
                "marketOutcomeSourceMaps":[
                   {
                      "id":198,
                      "marketOutcomeId":486,
                      "sourceId":2,
                      "sourceMarketOutcomeId":"87/1711",
                      "marketOutcomeSourceMapSpecials":[
 
                      ]
                   }
                ]
             },
             "487":{
                "id":487,
                "marketId":93,
                "sourceId":1,
                "name":"X",
                "active":1,
                "marketOutcomeSourceMaps":[
                   {
                      "id":199,
                      "marketOutcomeId":487,
                      "sourceId":2,
                      "sourceMarketOutcomeId":"87/1712",
                      "marketOutcomeSourceMapSpecials":[
 
                      ]
                   }
                ]
             },
             "578":{
                "id":578,
                "marketId":93,
                "sourceId":1,
                "name":"2",
                "active":1,
                "marketOutcomeSourceMaps":[
                   {
                      "id":200,
                      "marketOutcomeId":578,
                      "sourceId":2,
                      "sourceMarketOutcomeId":"87/1713",
                      "marketOutcomeSourceMapSpecials":[
 
                      ]
                   }
                ]
             }
          },
          "marketSpecialValues":{
             "41":{
                "id":41,
                "marketId":93,
                "specialTypeId":2,
                "name":"",
                "deleted":0
             }
          },
          "marketSourceMaps":[
             {
                "id":84,
                "marketId":93,
                "sourceId":2,
                "sourceMarketId":"87",
                "marketSourceMapSpecials":[
                   {
                      "id":45,
                      "marketSourceMapId":84,
                      "specialTypeId":2,
                      "specialValue":"",
                      "betradarSpecialType":"hcp"
                   }
                ]
             }
          ],
          "marketCompetitors":[
 
          ]
       },
       "119":{
          "id":119,
          "name":"PRVO POLUVRIJEME DUPLA SANSA",
          "sourceId":1,
          "eventType":1,
          "isCompetitor":0,
          "marketOutcomes":{
             "531":{
                "id":531,
                "marketId":119,
                "sourceId":1,
                "name":"12",
                "active":1,
                "marketOutcomeSourceMaps":[
                   {
                      "id":157,
                      "marketOutcomeId":531,
                      "sourceId":2,
                      "sourceMarketOutcomeId":"63/10",
                      "marketOutcomeSourceMapSpecials":[
 
                      ]
                   }
                ]
             },
             "532":{
                "id":532,
                "marketId":119,
                "sourceId":1,
                "name":"1X",
                "active":1,
                "marketOutcomeSourceMaps":[
                   {
                      "id":158,
                      "marketOutcomeId":532,
                      "sourceId":2,
                      "sourceMarketOutcomeId":"63/9",
                      "marketOutcomeSourceMapSpecials":[
 
                      ]
                   }
                ]
             },
             "533":{
                "id":533,
                "marketId":119,
                "sourceId":1,
                "name":"X2",
                "active":1,
                "marketOutcomeSourceMaps":[
                   {
                      "id":159,
                      "marketOutcomeId":533,
                      "sourceId":2,
                      "sourceMarketOutcomeId":"63/11",
                      "marketOutcomeSourceMapSpecials":[
 
                      ]
                   }
                ]
             }
          },
          "marketSpecialValues":[
 
          ],
          "marketSourceMaps":[
             {
                "id":106,
                "marketId":119,
                "sourceId":2,
                "sourceMarketId":"63",
                "marketSourceMapSpecials":[
 
                ]
             }
          ],
          "marketCompetitors":[
 
          ]
       },
       "137":{
          "id":137,
          "name":"Dupla Šansa (NEW)",
          "sourceId":1,
          "eventType":1,
          "isCompetitor":0,
          "marketOutcomes":{
             "566":{
                "id":566,
                "marketId":137,
                "sourceId":1,
                "name":"1X",
                "active":1,
                "marketOutcomeSourceMaps":[
 
                ]
             },
             "567":{
                "id":567,
                "marketId":137,
                "sourceId":1,
                "name":"12",
                "active":1,
                "marketOutcomeSourceMaps":[
 
                ]
             },
             "568":{
                "id":568,
                "marketId":137,
                "sourceId":1,
                "name":"X2",
                "active":1,
                "marketOutcomeSourceMaps":[
 
                ]
             }
          },
          "marketSpecialValues":[
 
          ],
          "marketSourceMaps":[
 
          ],
          "marketCompetitors":[
 
          ]
       }
    },
    "eventCompetitors":[
       {
          "id":2132727,
          "eventId":970353,
          "teamId":177,
          "playerId":0,
          "type":1,
          "name":"SKU Amstetten",
          "players":[
 
          ]
       },
       {
          "id":2132728,
          "eventId":970353,
          "teamId":1575,
          "playerId":0,
          "type":2,
          "name":"SK Austria Klagenfurt",
          "players":[
 
          ]
       }
    ],
    "eventMarkets":[
       {
          "id":12357480,
          "eventId":970353,
          "marketId":137,
          "favourite":0,
          "status":1,
          "active":1,
          "deleted":0,
          "eventMarketSpecials":[
 
          ],
          "eventMarketOutcomes":[
             {
                "id":28122607,
                "eventMarketId":12357480,
                "marketOutcomeId":566,
                "status":1,
                "odd":"2.350000"
             },
             {
                "id":28122608,
                "eventMarketId":12357480,
                "marketOutcomeId":567,
                "status":1,
                "odd":"1.250000"
             },
             {
                "id":28122609,
                "eventMarketId":12357480,
                "marketOutcomeId":568,
                "status":1,
                "odd":"1.130000"
             }
          ],
          "eventMarketCompetitors":[
 
          ]
       },
       {
          "id":12357481,
          "eventId":970353,
          "marketId":24,
          "favourite":0,
          "status":1,
          "active":1,
          "deleted":0,
          "eventMarketSpecials":[
 
          ],
          "eventMarketOutcomes":[
             {
                "id":28122610,
                "eventMarketId":12357481,
                "marketOutcomeId":238,
                "status":1,
                "odd":"4.280000"
             },
             {
                "id":28122611,
                "eventMarketId":12357481,
                "marketOutcomeId":239,
                "status":1,
                "odd":"1.190000"
             }
          ],
          "eventMarketCompetitors":[
 
          ]
       },
       {
          "id":12357482,
          "eventId":970353,
          "marketId":14,
          "favourite":0,
          "status":1,
          "active":1,
          "deleted":0,
          "eventMarketSpecials":[
 
          ],
          "eventMarketOutcomes":[
             {
                "id":28122612,
                "eventMarketId":12357482,
                "marketOutcomeId":130,
                "status":1,
                "odd":"4.900000"
             },
             {
                "id":28122613,
                "eventMarketId":12357482,
                "marketOutcomeId":132,
                "status":1,
                "odd":"2.700000"
             },
             {
                "id":28122614,
                "eventMarketId":12357482,
                "marketOutcomeId":134,
                "status":1,
                "odd":"2.070000"
             }
          ],
          "eventMarketCompetitors":[
 
          ]
       },
       {
          "id":12357483,
          "eventId":970353,
          "marketId":93,
          "favourite":1,
          "status":1,
          "active":1,
          "deleted":0,
          "eventMarketSpecials":[
             {
                "id":8774042,
                "eventMarketId":12357483,
                "marketSpecialValueId":41,
                "specialValue":"1:0"
             }
          ],
          "eventMarketOutcomes":[
             {
                "id":28122615,
                "eventMarketId":12357483,
                "marketOutcomeId":486,
                "status":1,
                "odd":"1.980000"
             },
             {
                "id":28122616,
                "eventMarketId":12357483,
                "marketOutcomeId":487,
                "status":1,
                "odd":"3.450000"
             },
             {
                "id":28122617,
                "eventMarketId":12357483,
                "marketOutcomeId":578,
                "status":1,
                "odd":"4.000000"
             }
          ],
          "eventMarketCompetitors":[
 
          ]
       },
       {
          "id":12357484,
          "eventId":970353,
          "marketId":31,
          "favourite":0,
          "status":1,
          "active":1,
          "deleted":0,
          "eventMarketSpecials":[
 
          ],
          "eventMarketOutcomes":[
             {
                "id":28122618,
                "eventMarketId":12357484,
                "marketOutcomeId":192,
                "status":1,
                "odd":"3.200000"
             },
             {
                "id":28122619,
                "eventMarketId":12357484,
                "marketOutcomeId":193,
                "status":1,
                "odd":"4.200000"
             },
             {
                "id":28122620,
                "eventMarketId":12357484,
                "marketOutcomeId":194,
                "status":1,
                "odd":"1.980000"
             }
          ],
          "eventMarketCompetitors":[
 
          ]
       },
       {
          "id":12357485,
          "eventId":970353,
          "marketId":16,
          "favourite":0,
          "status":1,
          "active":1,
          "deleted":0,
          "eventMarketSpecials":[
 
          ],
          "eventMarketOutcomes":[
             {
                "id":28122621,
                "eventMarketId":12357485,
                "marketOutcomeId":152,
                "status":1,
                "odd":"1.800000"
             },
             {
                "id":28122622,
                "eventMarketId":12357485,
                "marketOutcomeId":155,
                "status":1,
                "odd":"1.540000"
             },
             {
                "id":28122623,
                "eventMarketId":12357485,
                "marketOutcomeId":160,
                "status":1,
                "odd":"1.230000"
             }
          ],
          "eventMarketCompetitors":[
 
          ]
       },
       {
          "id":12357486,
          "eventId":970353,
          "marketId":119,
          "favourite":0,
          "status":1,
          "active":1,
          "deleted":0,
          "eventMarketSpecials":[
 
          ],
          "eventMarketOutcomes":[
             {
                "id":28122624,
                "eventMarketId":12357486,
                "marketOutcomeId":531,
                "status":1,
                "odd":"6.540000"
             },
             {
                "id":28122625,
                "eventMarketId":12357486,
                "marketOutcomeId":532,
                "status":1,
                "odd":"1.800000"
             },
             {
                "id":28122626,
                "eventMarketId":12357486,
                "marketOutcomeId":533,
                "status":1,
                "odd":"1.230000"
             }
          ],
          "eventMarketCompetitors":[
 
          ]
       }
    ]
 }